ec2_spot_price/__init__.py
ec2_spot_price/ec2_spot_price.py
ec2_spot_price-0.2.3.dist-info/entry_points.txt
ec2_spot_price-0.2.3.dist-info/LICENSE
ec2_spot_price-0.2.3.dist-info/WHEEL
ec2_spot_price-0.2.3.dist-info/METADATA
ec2_spot_price-0.2.3.dist-info/RECORD
