Metadata-Version: 2.1
Name: ec2-spot-price
Version: 0.2.3
Summary: ec2-spot-price: retrieve Amazon EC2 spot instance price
Home-page: https://github.com/susumuota/ec2-spot-price
License: Apache-2.0
Keywords: amazon,aws,ec2,spot instance,price
Author: Susumu OTA
Author-email: 1632335+susumuota@users.noreply.github.com
Requires-Python: >=3.7.1,<4.0.0
Classifier: Development Status :: 4 - Beta
Classifier: License :: OSI Approved :: Apache Software License
Classifier: Programming Language :: Python
Classifier: Programming Language :: Python :: 3
Classifier: Programming Language :: Python :: 3.7
Classifier: Programming Language :: Python :: 3.8
Classifier: Programming Language :: Python :: 3.9
Classifier: Topic :: Software Development :: Libraries
Classifier: Topic :: Software Development :: Libraries :: Python Modules
Classifier: Topic :: Utilities
Requires-Dist: boto3 (>=1.17.17,<2.0.0)
Requires-Dist: importlib-metadata (>=3.7.0,<4.0.0); python_version < "3.8"
Requires-Dist: pandas (>=1.2.2,<2.0.0)
Requires-Dist: rich (>=9.12.1,<10.0.0)
Project-URL: Documentation, https://github.com/susumuota/ec2-spot-price
Project-URL: Repository, https://github.com/susumuota/ec2-spot-price
